israel_bus_cli/__init__.py
israel_bus_cli/__main__.py
israel_bus_cli/bus_info.py
israel_bus_cli/cli.py
israel_bus_cli-0.1.1.dist-info/licenses/LICENSE
israel_bus_cli-0.1.1.dist-info/METADATA
israel_bus_cli-0.1.1.dist-info/WHEEL
israel_bus_cli-0.1.1.dist-info/entry_points.txt
israel_bus_cli-0.1.1.dist-info/top_level.txt
israel_bus_cli-0.1.1.dist-info/RECORD
