Metadata-Version: 2.4
Name: israel-bus-cli
Version: 0.1.1
Summary: CLI + Python API to search Israeli bus stops and realtime line arrivals
Author-email: Ben Cohen <benxcohen@gmail.com>
License: MIT
Project-URL: Homepage, https://github.com/Strike24/israel_bus_cli
Project-URL: Issues, https://github.com/Strike24/israel_bus_cli/issues
Keywords: israel,bus,transport,cli,public-transit
Classifier: Programming Language :: Python :: 3
Classifier: Programming Language :: Python :: 3.9
Classifier: Programming Language :: Python :: 3.10
Classifier: Programming Language :: Python :: 3.11
Classifier: Programming Language :: Python :: 3.12
Classifier: License :: OSI Approved :: MIT License
Classifier: Operating System :: OS Independent
Classifier: Intended Audience :: End Users/Desktop
Classifier: Intended Audience :: Developers
Classifier: Topic :: Utilities
Classifier: Topic :: Internet :: WWW/HTTP :: Indexing/Search
Requires-Python: >=3.9
License-File: LICENSE
Requires-Dist: requests>=2.31.0
Requires-Dist: python-bidi>=0.4.2
Dynamic: license-file
